kwexception/__init__.py
kwexception/main.py
kwexception/version.py
kwexception-1.0.0.dist-info/LICENSE
kwexception-1.0.0.dist-info/METADATA
kwexception-1.0.0.dist-info/WHEEL
kwexception-1.0.0.dist-info/top_level.txt
kwexception-1.0.0.dist-info/RECORD
