Metadata-Version: 2.1
Name: kwexception
Version: 1.0.0
Summary: Better exceptions with keyword parameters
Home-page: https://github.com/hindman/kwexception
Author: Monty Hindman
Author-email: mhindman@gmail.com
License: MIT
Classifier: Development Status :: 5 - Production/Stable
Classifier: Intended Audience :: Developers
Classifier: License :: OSI Approved :: MIT License
Classifier: Operating System :: OS Independent
Classifier: Programming Language :: Python :: 3
Classifier: Topic :: Software Development
License-File: LICENSE
Provides-Extra: dev
Requires-Dist: invoke ; extra == 'dev'
Requires-Dist: ipython ; extra == 'dev'
Requires-Dist: pycodestyle ; extra == 'dev'
Requires-Dist: twine ; extra == 'dev'
Requires-Dist: virtualenv ; extra == 'dev'
Requires-Dist: virtualenvwrapper ; extra == 'dev'
Provides-Extra: test
Requires-Dist: pytest-cov ; extra == 'test'
Requires-Dist: tox ; extra == 'test'
